hook/__init__.py
hook/stack_termination_protection.py
sceptre_stack_termination_protection_hook-1.1.0.dist-info/METADATA
sceptre_stack_termination_protection_hook-1.1.0.dist-info/WHEEL
sceptre_stack_termination_protection_hook-1.1.0.dist-info/entry_points.txt
sceptre_stack_termination_protection_hook-1.1.0.dist-info/top_level.txt
sceptre_stack_termination_protection_hook-1.1.0.dist-info/RECORD
