Metadata-Version: 2.1
Name: sceptre-stack-termination-protection-hook
Version: 1.1.0
Summary: A Sceptre hook to enable and disable stack termination protection
Home-page: https://github.com/sceptre/sceptre-stack-termination-protection-hook
Author: zaro0508
Author-email: zaro0508@gmail.com
License: Apache2
Keywords: sceptre,sceptre-hook
Platform: UNKNOWN
Classifier: Intended Audience :: Developers
Classifier: Natural Language :: English
Classifier: Environment :: Console
Classifier: Programming Language :: Python :: 2.7
Classifier: Programming Language :: Python :: 3.5
Classifier: Programming Language :: Python :: 3.6
Classifier: Programming Language :: Python :: 3.7
Requires-Dist: packaging (==16.8)
Provides-Extra: test
Requires-Dist: pytest (>=3.2) ; extra == 'test'
